odoo8_addon_service_desk_issue-8.0.1.1.0.99.dev22-py3.8-nspkg.pth
odoo_addons/service_desk_issue/__init__.py
odoo_addons/service_desk_issue/__openerp__.py
odoo_addons/service_desk_issue/project.py
odoo_addons/service_desk_issue/service_desk_view.xml
odoo_addons/service_desk_issue/i18n/ca.po
odoo_addons/service_desk_issue/i18n/de.po
odoo_addons/service_desk_issue/i18n/es.po
odoo_addons/service_desk_issue/i18n/es_ES.po
odoo_addons/service_desk_issue/i18n/fi.po
odoo_addons/service_desk_issue/i18n/fr.po
odoo_addons/service_desk_issue/i18n/hr.po
odoo_addons/service_desk_issue/i18n/it.po
odoo_addons/service_desk_issue/i18n/nl_NL.po
odoo_addons/service_desk_issue/i18n/pt.po
odoo_addons/service_desk_issue/i18n/pt_BR.po
odoo_addons/service_desk_issue/i18n/pt_PT.po
odoo_addons/service_desk_issue/i18n/service_desk_issue.pot
odoo_addons/service_desk_issue/i18n/sl.po
odoo_addons/service_desk_issue/i18n/tr_TR.po
odoo_addons/service_desk_issue/i18n/zh_CN.po
odoo_addons/service_desk_issue/static/description/icon.png
odoo8_addon_service_desk_issue-8.0.1.1.0.99.dev22.dist-info/METADATA
odoo8_addon_service_desk_issue-8.0.1.1.0.99.dev22.dist-info/WHEEL
odoo8_addon_service_desk_issue-8.0.1.1.0.99.dev22.dist-info/namespace_packages.txt
odoo8_addon_service_desk_issue-8.0.1.1.0.99.dev22.dist-info/top_level.txt
odoo8_addon_service_desk_issue-8.0.1.1.0.99.dev22.dist-info/RECORD
